{
  "notes": [
    {
      "id": 1,
      "content": "HTML is easy",
      "important": false
    },
    {
      "id": 2,
      "content": "Browser can execute only JavaScript",
      "important": false
    },
    {
      "id": 3,
      "content": "GET and POST are the most important methods of HTTP protocol",
      "important": false
    },
    {
      "content": "hello js",
      "important": false,
      "id": 4
    },
    {
      "content": "hi",
      "important": false,
      "id": 5
    },
    {
      "content": "heloo",
      "important": false,
      "id": 6
    },
    {
      "content": "hi",
      "important": true,
      "id": 7
    },
    {
      "content": "vsfdvf",
      "important": false,
      "id": 8
    }
  ]
}